nychka/__config__.py
nychka/__init__.py
nychka/setup.py
nychka/distribution/__init__.py
nychka/distribution/cdf_ufunc.cp38-win_amd64.pyd
nychka/distribution/setup.py
nychka-0.0.3.dist-info/LICENSE
nychka-0.0.3.dist-info/METADATA
nychka-0.0.3.dist-info/WHEEL
nychka-0.0.3.dist-info/top_level.txt
nychka-0.0.3.dist-info/RECORD
